plonetheme.classic-1.5.1-py2.7-nspkg.pth
plonetheme/classic/__init__.py
plonetheme/classic/configure.zcml
plonetheme/classic/Extensions/install.py
plonetheme/classic/browser/__init__.py
plonetheme/classic/browser/configure.zcml
plonetheme/classic/browser/interfaces.py
plonetheme/classic/browser/personal_bar.pt
plonetheme/classic/profiles/default/cssregistry.xml
plonetheme/classic/profiles/default/metadata.xml
plonetheme/classic/profiles/default/skins.xml
plonetheme/classic/profiles/default/viewlets.xml
plonetheme/classic/profiles/uninstall/skins.xml
plonetheme/classic/skins/classic_ecmascript/iefixes.js
plonetheme/classic/skins/classic_styles/IEFixes.css.dtml
plonetheme/classic/skins/classic_styles/IEFixes.css.dtml.metadata
plonetheme/classic/skins/classic_styles/NS4.css.dtml
plonetheme/classic/skins/classic_styles/NS4.css.dtml.metadata
plonetheme/classic/skins/classic_styles/RTL.css.dtml
plonetheme/classic/skins/classic_styles/RTL.css.dtml.metadata
plonetheme/classic/skins/classic_styles/authoring.css.dtml
plonetheme/classic/skins/classic_styles/authoring.css.dtml.metadata
plonetheme/classic/skins/classic_styles/base.css.dtml
plonetheme/classic/skins/classic_styles/base.css.dtml.metadata
plonetheme/classic/skins/classic_styles/base_properties.props
plonetheme/classic/skins/classic_styles/columns.css.dtml
plonetheme/classic/skins/classic_styles/columns.css.dtml.metadata
plonetheme/classic/skins/classic_styles/controlpanel.css.dtml
plonetheme/classic/skins/classic_styles/controlpanel.css.dtml.metadata
plonetheme/classic/skins/classic_styles/deprecated.css.dtml
plonetheme/classic/skins/classic_styles/deprecated.css.dtml.metadata
plonetheme/classic/skins/classic_styles/forms.css.dtml
plonetheme/classic/skins/classic_styles/forms.css.dtml.metadata
plonetheme/classic/skins/classic_styles/invisibles.css.dtml
plonetheme/classic/skins/classic_styles/invisibles.css.dtml.metadata
plonetheme/classic/skins/classic_styles/member.css.dtml
plonetheme.classic-1.5.1.dist-info/METADATA
plonetheme.classic-1.5.1.dist-info/WHEEL
plonetheme.classic-1.5.1.dist-info/entry_points.txt
plonetheme.classic-1.5.1.dist-info/namespace_packages.txt
plonetheme.classic-1.5.1.dist-info/top_level.txt
plonetheme.classic-1.5.1.dist-info/RECORD
